sequential_parser-0.3.dist-info/RECORD
sequential_parser-0.3.dist-info/top_level.txt
sequential_parser-0.3.dist-info/DESCRIPTION.rst
sequential_parser-0.3.dist-info/METADATA
sequential_parser-0.3.dist-info/metadata.json
sequential_parser-0.3.dist-info/WHEEL
sequential_parser/utils.py
sequential_parser/__init__.py
